anyscale_provider/__init__.py
anyscale_provider/hooks/__init__.py
anyscale_provider/hooks/anyscale.py
anyscale_provider/operators/__init__.py
anyscale_provider/operators/anyscale.py
anyscale_provider/triggers/__init__.py
anyscale_provider/triggers/anyscale.py
astro_provider_anyscale-1.1.0.dist-info/METADATA
astro_provider_anyscale-1.1.0.dist-info/WHEEL
astro_provider_anyscale-1.1.0.dist-info/entry_points.txt
astro_provider_anyscale-1.1.0.dist-info/licenses/LICENSE
astro_provider_anyscale-1.1.0.dist-info/RECORD
